stock_scanner/Stock.py
stock_scanner/__init__.py
stock_scanner/condition/AboveTwoSMAs.py
stock_scanner/condition/Condition.py
stock_scanner/condition/Consolidating.py
stock_scanner/condition/__init__.py
stock_scanner/export/SaveTickersToFile.py
stock_scanner/export/SaveToInteractive.py
stock_scanner/export/SaveToPNG.py
stock_scanner/export/__init__.py
stock_scanner/io/StockIO.py
stock_scanner/io/YahooIO.py
stock_scanner/io/__init__.py
stock_scanner/scanner/BasicScanner.py
stock_scanner/scanner/Scanner.py
stock_scanner/scanner/__init__.py
stock_scanner/validator/BasicValidator.py
stock_scanner/validator/Validator.py
stock_scanner/validator/__init__.py
stock_scanner-0.0.14.dist-info/LICENSE
stock_scanner-0.0.14.dist-info/METADATA
stock_scanner-0.0.14.dist-info/WHEEL
stock_scanner-0.0.14.dist-info/top_level.txt
stock_scanner-0.0.14.dist-info/RECORD
