Metadata-Version: 2.1
Name: stock-scanner
Version: 0.0.14
Summary: A Python framework for building stock scanners/screeners.
Home-page: https://github.com/pypa/sampleproject
Author: Jon Cavallie Mester
Author-email: jonmester3@gmail.com
License: UNKNOWN
Project-URL: Bug Tracker, https://github.com/pypa/sampleproject/issues
Platform: UNKNOWN
Classifier: Programming Language :: Python :: 3
Classifier: License :: OSI Approved :: MIT License
Classifier: Operating System :: OS Independent
Requires-Python: >=3.6
License-File: LICENSE
